lb/nightly/configuration/__init__.py
lb/nightly/configuration/constants.py
lb/nightly/configuration/project.py
lb/nightly/configuration/slot.py
lb/nightly/configuration/utils.py
lb_nightly_configuration-0.3.2.dist-info/LICENSE
lb_nightly_configuration-0.3.2.dist-info/METADATA
lb_nightly_configuration-0.3.2.dist-info/WHEEL
lb_nightly_configuration-0.3.2.dist-info/entry_points.txt
lb_nightly_configuration-0.3.2.dist-info/RECORD
